example_tests/__init__.py
example_tests/test_base/__init__.py
example_tests/test_base/test_functions.py
example_tests/test_team_sports/__init__.py
example_tests/test_team_sports/test_team_sports.py
faux_sures/__init__.py
faux_sures/exceptions.py
faux_sures/not_db.py
faux_sures/recipes/__init__.py
faux_sures/recipes/curries.py
faux_sures/recipes/sauces.py
faux_sures-0.0.3.dist-info/LICENSE
faux_sures-0.0.3.dist-info/METADATA
faux_sures-0.0.3.dist-info/WHEEL
faux_sures-0.0.3.dist-info/top_level.txt
faux_sures-0.0.3.dist-info/RECORD
