Metadata-Version: 2.1
Name: faux-sures
Version: 0.0.3
Summary: A REPL for fast Model ProtoTyping
Home-page: https://github.com/aannapureddy/faux_sure
Author: Arjun Annapureddy
Author-email: arjun.annapureddy@gmail.com
License: UNKNOWN
Project-URL: Bug Tracker, https://github.com/aannapureddy/faux_sure/issues
Platform: UNKNOWN
Classifier: Programming Language :: Python :: 3
Classifier: License :: OSI Approved :: MIT License
Classifier: Operating System :: OS Independent
Requires-Python: >=3.6
License-File: LICENSE
